Metadata-Version: 1.0
Name: mlnd-distributions-rv
Version: 0.1
Summary: Distributions containing Gaussian and Binomial Distributions
Home-page: UNKNOWN
Author: Rahul Vaswani
Author-email: firstname_first3lettersoflast@gmail.com
License: UNKNOWN
Platform: UNKNOWN
